cm_service_library/__init__.py
cm_service_library/crypto.py
cm_service_library/helpers.py
cm_service_library/middleware.py
cm_service_library/serialiser.py
cm_service_library-0.0.5.dist-info/METADATA
cm_service_library-0.0.5.dist-info/WHEEL
cm_service_library-0.0.5.dist-info/top_level.txt
cm_service_library-0.0.5.dist-info/RECORD
