Metadata-Version: 2.1
Name: cm-service-library
Version: 0.0.5
Summary: Just another module library
Home-page: https://gitlab.com/cloudmicro/pypi/service_library
Author: Trent Murray
Author-email: trent@cloudmicro.io
License: UNKNOWN
Platform: UNKNOWN
Classifier: Programming Language :: Python :: 3
Classifier: License :: OSI Approved :: MIT License
Classifier: Operating System :: OS Independent
Requires-Dist: secure
